berlin_de_appointment_finder/__init__.py
berlin_de_appointment_finder/cli.py
berlin_de_appointment_finder/service.py
berlin_de_appointment_finder/telegram.py
berlin_de_appointment_finder-0.1.dist-info/METADATA
berlin_de_appointment_finder-0.1.dist-info/WHEEL
berlin_de_appointment_finder-0.1.dist-info/entry_points.txt
berlin_de_appointment_finder-0.1.dist-info/RECORD
